test_fibonacci_numbers/__init__.py
test_fibonacci_numbers/fibonacci_numbers.py
test_fibonacci_numbers-0.0.1.dist-info/LICENCE.txt
test_fibonacci_numbers-0.0.1.dist-info/METADATA
test_fibonacci_numbers-0.0.1.dist-info/WHEEL
test_fibonacci_numbers-0.0.1.dist-info/top_level.txt
test_fibonacci_numbers-0.0.1.dist-info/RECORD
