Metadata-Version: 2.1
Name: test-fibonacci-numbers
Version: 0.0.1
Summary: test project
Author: Levi011
Author-email: tornike.davitashvili.2@btu.edu.ge
Classifier: Programming Language :: Python :: 3
Classifier: License :: OSI Approved :: MIT License
Classifier: Operating System :: OS Independent
Requires-Python: >=3.6
License-File: LICENCE.txt
